github_avatar_dl/__init__.py
github_avatar_dl-1.2.dist-info/LICENSE
github_avatar_dl-1.2.dist-info/METADATA
github_avatar_dl-1.2.dist-info/WHEEL
github_avatar_dl-1.2.dist-info/top_level.txt
github_avatar_dl-1.2.dist-info/RECORD
