Metadata-Version: 2.1
Name: github-avatar-dl
Version: 1.2
Summary: A python module that will allow users to download GitHub avatar images
Home-page: https://github.com/mehtaarn000/github-avatar-dl
Author: Arnav Mehta
License: UNKNOWN
Platform: UNKNOWN
Classifier: Programming Language :: Python :: 3
Classifier: License :: OSI Approved :: MIT License
Classifier: Operating System :: OS Independent
